asciidraw/__init__.py
asciidraw/label.py
asciidraw/line.py
asciidraw/pane.py
asciidraw/point.py
asciidraw/style.py
asciidraw-0.1.2.dist-info/AUTHORS
asciidraw-0.1.2.dist-info/LICENSE
asciidraw-0.1.2.dist-info/METADATA
asciidraw-0.1.2.dist-info/WHEEL
asciidraw-0.1.2.dist-info/RECORD
